mkdocs_material_mark_as_read/__init__.py
mkdocs_material_mark_as_read/config.py
mkdocs_material_mark_as_read/plugin.py
mkdocs_material_mark_as_read/css/mark-as-read-button.css
mkdocs_material_mark_as_read/js/mark-as-read-button.js
mkdocs_material_mark_as_read/js/mark-as-read-navlink-updater.js
mkdocs_material_mark_as_read-0.0.1.dist-info/METADATA
mkdocs_material_mark_as_read-0.0.1.dist-info/WHEEL
mkdocs_material_mark_as_read-0.0.1.dist-info/entry_points.txt
mkdocs_material_mark_as_read-0.0.1.dist-info/licenses/LICENSE
mkdocs_material_mark_as_read-0.0.1.dist-info/RECORD
