Metadata-Version: 2.3
Name: mkdocs-material-mark-as-read
Version: 0.0.1
Summary: A mkdocs-material plugin to mark pages as read
Project-URL: Documentation, https://berk-karaal.github.io/mkdocs-material-mark-as-read/
Project-URL: Repository, https://github.com/berk-karaal/mkdocs-material-mark-as-read.git
Maintainer-email: Berk Karaal <iletisim.berkkaraal@gmail.com>
License: MIT License
License-File: LICENSE
Requires-Python: >=3.9
Requires-Dist: mkdocs
